webxdcbot/__init__.py
webxdcbot/__main__.py
webxdcbot/app.py
webxdcbot/app.xdc
webxdcbot-0.1.0.dist-info/LICENSE
webxdcbot-0.1.0.dist-info/METADATA
webxdcbot-0.1.0.dist-info/WHEEL
webxdcbot-0.1.0.dist-info/entry_points.txt
webxdcbot-0.1.0.dist-info/top_level.txt
webxdcbot-0.1.0.dist-info/RECORD
