Metadata-Version: 2.1
Name: webxdcbot
Version: 0.1.0
Summary: Example Delta Chat bot + webxdc app
Author-email: adbenitez <adbenitez@hispanilandia.net>
Keywords: deltachat,bot
Classifier: Development Status :: 4 - Beta
Classifier: Programming Language :: Python
Requires-Python: >=3.8
License-File: LICENSE
Requires-Dist: deltabot-cli
Requires-Dist: fortune-python
Provides-Extra: dev
Requires-Dist: black ; extra == 'dev'
Requires-Dist: mypy ; extra == 'dev'
Requires-Dist: isort ; extra == 'dev'
Requires-Dist: pylint ; extra == 'dev'
Requires-Dist: pylama ; extra == 'dev'
Requires-Dist: pytest ; extra == 'dev'
